[
    {
        "key": "group_5c115706c6eb8",
        "title": "Agency Fields",
        "fields": [
            {
                "key": "field_5c11697dcad3b",
                "label": "Agency Name",
                "name": "agency",
                "type": "select",
                "instructions": "",
                "required": 0,
                "conditional_logic": 0,
                "wrapper": {
                    "width": "",
                    "class": "",
                    "id": ""
                },
                "choices": {
                    "Agriculture & Life Sciences": "Agriculture & Life Sciences",
                    "TVMDL": "TVMDL",
                    "Forest Service": "Forest Service",
                    "Extension": "Extension",
                    "Research": "Research"
                },
                "default_value": [],
                "allow_null": 0,
                "multiple": 0,
                "ui": 0,
                "return_format": "value",
                "ajax": 0,
                "placeholder": ""
            },
            {
                "key": "field_5c115e89cad35",
                "label": "Site Link",
                "name": "site_link",
                "type": "link",
                "instructions": "",
                "required": 0,
                "conditional_logic": 0,
                "wrapper": {
                    "width": "",
                    "class": "",
                    "id": ""
                },
                "return_format": "url"
            },
            {
                "key": "field_5c18052a4f66c",
                "label": "Flowchart Details",
                "name": "flowchart_group",
                "type": "group",
                "instructions": "",
                "required": 0,
                "conditional_logic": 0,
                "wrapper": {
                    "width": "",
                    "class": "",
                    "id": ""
                },
                "layout": "block",
                "sub_fields": [
                    {
                        "key": "field_5c180baa68bdf",
                        "label": "Title",
                        "name": "title",
                        "type": "text",
                        "instructions": "",
                        "required": 0,
                        "conditional_logic": 0,
                        "wrapper": {
                            "width": "",
                            "class": "",
                            "id": ""
                        },
                        "default_value": "Resources by Agency",
                        "placeholder": "",
                        "prepend": "",
                        "append": "",
                        "maxlength": ""
                    }
                ]
            },
            {
                "key": "field_5c116ab7cad3c",
                "label": "Flowchart Items",
                "name": "flowchart",
                "type": "repeater",
                "instructions": "",
                "required": 0,
                "conditional_logic": 0,
                "wrapper": {
                    "width": "",
                    "class": "",
                    "id": ""
                },
                "collapsed": "",
                "min": 0,
                "max": 0,
                "layout": "table",
                "button_label": "Add Item",
                "sub_fields": [
                    {
                        "key": "field_5c116ad3cad3d",
                        "label": "Text",
                        "name": "text",
                        "type": "text",
                        "instructions": "",
                        "required": 0,
                        "conditional_logic": 0,
                        "wrapper": {
                            "width": "",
                            "class": "",
                            "id": ""
                        },
                        "default_value": "",
                        "placeholder": "",
                        "prepend": "",
                        "append": "",
                        "maxlength": ""
                    },
                    {
                        "key": "field_5c116b22cad3e",
                        "label": "Link",
                        "name": "link",
                        "type": "link",
                        "instructions": "",
                        "required": 0,
                        "conditional_logic": 0,
                        "wrapper": {
                            "width": "",
                            "class": "",
                            "id": ""
                        },
                        "return_format": "url"
                    }
                ]
            },
            {
                "key": "field_5c3e00b4d9267",
                "label": "Resources",
                "name": "resources",
                "type": "group",
                "instructions": "",
                "required": 0,
                "conditional_logic": 0,
                "wrapper": {
                    "width": "",
                    "class": "",
                    "id": ""
                },
                "layout": "block",
                "sub_fields": [
                    {
                        "key": "field_5c3e00b4d9269",
                        "label": "Items",
                        "name": "items",
                        "type": "repeater",
                        "instructions": "",
                        "required": 0,
                        "conditional_logic": 0,
                        "wrapper": {
                            "width": "",
                            "class": "",
                            "id": ""
                        },
                        "collapsed": "",
                        "min": 0,
                        "max": 0,
                        "layout": "row",
                        "button_label": "Add Item",
                        "sub_fields": [
                            {
                                "key": "field_5c3e00b4d926b",
                                "label": "Title",
                                "name": "title",
                                "type": "text",
                                "instructions": "",
                                "required": 0,
                                "conditional_logic": 0,
                                "wrapper": {
                                    "width": "",
                                    "class": "",
                                    "id": ""
                                },
                                "default_value": "",
                                "placeholder": "",
                                "prepend": "",
                                "append": "",
                                "maxlength": ""
                            },
                            {
                                "key": "field_5c3e00b4d926a",
                                "label": "Image",
                                "name": "image",
                                "type": "image",
                                "instructions": "",
                                "required": 0,
                                "conditional_logic": 0,
                                "wrapper": {
                                    "width": "",
                                    "class": "",
                                    "id": ""
                                },
                                "return_format": "array",
                                "preview_size": "medium",
                                "library": "all",
                                "min_width": 360,
                                "min_height": "",
                                "min_size": "",
                                "max_width": "",
                                "max_height": "",
                                "max_size": "",
                                "mime_types": "jpg"
                            }
                        ]
                    }
                ]
            },
            {
                "key": "field_5c3cc5855fcdd",
                "label": "Infographic",
                "name": "infographic",
                "type": "group",
                "instructions": "",
                "required": 0,
                "conditional_logic": 0,
                "wrapper": {
                    "width": "",
                    "class": "",
                    "id": ""
                },
                "layout": "block",
                "sub_fields": [
                    {
                        "key": "field_5c3cc59e5fcde",
                        "label": "Image",
                        "name": "image",
                        "type": "image",
                        "instructions": "",
                        "required": 0,
                        "conditional_logic": 0,
                        "wrapper": {
                            "width": "",
                            "class": "",
                            "id": ""
                        },
                        "return_format": "array",
                        "preview_size": "medium",
                        "library": "all",
                        "min_width": "",
                        "min_height": "",
                        "min_size": "",
                        "max_width": "",
                        "max_height": "",
                        "max_size": "",
                        "mime_types": ""
                    }
                ]
            },
            {
                "key": "field_5c116ba3cad3f",
                "label": "Exceptional Items",
                "name": "exceptional_items",
                "type": "group",
                "instructions": "",
                "required": 0,
                "conditional_logic": 0,
                "wrapper": {
                    "width": "",
                    "class": "",
                    "id": ""
                },
                "layout": "block",
                "sub_fields": [
                    {
                        "key": "field_5c116be7cad40",
                        "label": "Introduction",
                        "name": "introduction",
                        "type": "wysiwyg",
                        "instructions": "",
                        "required": 0,
                        "conditional_logic": 0,
                        "wrapper": {
                            "width": "",
                            "class": "",
                            "id": ""
                        },
                        "default_value": "",
                        "tabs": "visual",
                        "toolbar": "simple_text",
                        "media_upload": 0,
                        "delay": 0
                    },
                    {
                        "key": "field_5c116c32cad41",
                        "label": "Items",
                        "name": "items",
                        "type": "repeater",
                        "instructions": "",
                        "required": 0,
                        "conditional_logic": 0,
                        "wrapper": {
                            "width": "",
                            "class": "",
                            "id": ""
                        },
                        "collapsed": "",
                        "min": 0,
                        "max": 0,
                        "layout": "row",
                        "button_label": "Add Item",
                        "sub_fields": [
                            {
                                "key": "field_5c116c48cad42",
                                "label": "Image",
                                "name": "image",
                                "type": "image",
                                "instructions": "",
                                "required": 0,
                                "conditional_logic": 0,
                                "wrapper": {
                                    "width": "",
                                    "class": "",
                                    "id": ""
                                },
                                "return_format": "array",
                                "preview_size": "medium",
                                "library": "all",
                                "min_width": 496,
                                "min_height": "",
                                "min_size": "",
                                "max_width": "",
                                "max_height": "",
                                "max_size": "",
                                "mime_types": "jpg"
                            },
                            {
                                "key": "field_5c116c78cad43",
                                "label": "Title",
                                "name": "title",
                                "type": "text",
                                "instructions": "",
                                "required": 0,
                                "conditional_logic": 0,
                                "wrapper": {
                                    "width": "",
                                    "class": "",
                                    "id": ""
                                },
                                "default_value": "",
                                "placeholder": "",
                                "prepend": "",
                                "append": "",
                                "maxlength": ""
                            },
                            {
                                "key": "field_5c17aecf8471a",
                                "label": "Link",
                                "name": "link",
                                "type": "link",
                                "instructions": "",
                                "required": 0,
                                "conditional_logic": 0,
                                "wrapper": {
                                    "width": "",
                                    "class": "",
                                    "id": ""
                                },
                                "return_format": "url"
                            },
                            {
                                "key": "field_5c116c7ecad44",
                                "label": "Description",
                                "name": "description",
                                "type": "wysiwyg",
                                "instructions": "",
                                "required": 0,
                                "conditional_logic": 0,
                                "wrapper": {
                                    "width": "",
                                    "class": "",
                                    "id": ""
                                },
                                "default_value": "",
                                "tabs": "visual",
                                "toolbar": "simple_text",
                                "media_upload": 0,
                                "delay": 0
                            }
                        ]
                    }
                ]
            },
            {
                "key": "field_5c115ed6cad36",
                "label": "Director",
                "name": "director",
                "type": "group",
                "instructions": "",
                "required": 0,
                "conditional_logic": 0,
                "wrapper": {
                    "width": "",
                    "class": "",
                    "id": ""
                },
                "layout": "row",
                "sub_fields": [
                    {
                        "key": "field_5c116943cad3a",
                        "label": "Name",
                        "name": "name",
                        "type": "text",
                        "instructions": "",
                        "required": 0,
                        "conditional_logic": 0,
                        "wrapper": {
                            "width": "",
                            "class": "",
                            "id": ""
                        },
                        "default_value": "",
                        "placeholder": "",
                        "prepend": "",
                        "append": "",
                        "maxlength": ""
                    },
                    {
                        "key": "field_5c17d08e91b5a",
                        "label": "Photo",
                        "name": "photo",
                        "type": "image",
                        "instructions": "",
                        "required": 0,
                        "conditional_logic": 0,
                        "wrapper": {
                            "width": "",
                            "class": "",
                            "id": ""
                        },
                        "return_format": "array",
                        "preview_size": "medium",
                        "library": "all",
                        "min_width": "",
                        "min_height": "",
                        "min_size": "",
                        "max_width": "",
                        "max_height": "",
                        "max_size": "",
                        "mime_types": "jpg"
                    },
                    {
                        "key": "field_5c115ef2cad37",
                        "label": "Quote",
                        "name": "quote",
                        "type": "textarea",
                        "instructions": "",
                        "required": 0,
                        "conditional_logic": 0,
                        "wrapper": {
                            "width": "",
                            "class": "",
                            "id": ""
                        },
                        "default_value": "",
                        "placeholder": "",
                        "maxlength": "",
                        "rows": "",
                        "new_lines": ""
                    },
                    {
                        "key": "field_5c115f45cad38",
                        "label": "Contact Info",
                        "name": "contact_info",
                        "type": "wysiwyg",
                        "instructions": "",
                        "required": 0,
                        "conditional_logic": 0,
                        "wrapper": {
                            "width": "",
                            "class": "",
                            "id": ""
                        },
                        "default_value": "",
                        "tabs": "visual",
                        "toolbar": "simple_text",
                        "media_upload": 0,
                        "delay": 0
                    }
                ]
            },
            {
                "key": "field_5c116cdecad45",
                "label": "Strategic Plan",
                "name": "strategic_plan",
                "type": "file",
                "instructions": "",
                "required": 0,
                "conditional_logic": 0,
                "wrapper": {
                    "width": "",
                    "class": "",
                    "id": ""
                },
                "return_format": "url",
                "library": "all",
                "min_size": "",
                "max_size": "",
                "mime_types": ""
            }
        ],
        "location": [
            [
                {
                    "param": "post_type",
                    "operator": "==",
                    "value": "agency"
                }
            ]
        ],
        "menu_order": 0,
        "position": "normal",
        "style": "default",
        "label_placement": "top",
        "instruction_placement": "label",
        "hide_on_screen": "",
        "active": 1,
        "description": ""
    }
]
